[
    {
      "slug": "ginkgo-biloba-500",
      "name": "Гинкго Билоба 500 мг",
      "short": "Память, внимание, кровообращение мозга",
      "category": "Растительные экстракты",
      "image": "images/ginkgo-biloba-500.jpg",
      "description": "Поддержка мозгового кровообращения и когнитивных функций: память, концентрация, координация. Снижение шума в ушах и головокружения, помощь при утомлении.",
      "facts": [
        {"name": "Форма", "value": "Капсулы, 60 шт."},
        {"name": "Порция", "value": "1 капсула"},
        {"name": "Состав на порцию", "value": "Экстракт листьев Гинкго билоба — 500 мг; Экстракт корней женьшеня — 20 мг; Цитиколин — 15 мг"}
      ]
    },
    {
      "slug": "magnesium-b6",
      "name": "Магний B6",
      "short": "Нервная система, сон, усвоение магния",
      "category": "Минералы",
      "image": "images/magnesium-b6.jpg",
      "description": "Магний участвует во множестве обменных процессов, помогает при раздражительности, спазмах мышц и нарушениях сна. Витамин B6 поддерживает нервную систему и улучшает усвоение магния.",
      "facts": [
        {"name": "Форма", "value": "Капсулы, 30 шт."},
        {"name": "Состав на 1 мл", "value": "Таурата магния (Mg) — 450 мг; Магния малат (Mg) — 250 мг; Витамин B6 — 5 мг"}
      ]
    },
    {
      "slug": "burdock-extract",
      "name": "Экстракт Лопуха 500 мг",
      "short": "Общий тонус, противовоспалительный эффект",
      "category": "Растительные экстракты",
      "image": "images/burdock.jpg",
      "description": "Оказывает оздоравливающий эффект на организм, способствует заживлению, помогает при воспалениях, нормализует вес и давление, выводит токсины и уменьшает отёки.",
      "facts": [
        {"name": "Форма", "value": "Капсулы, 60 шт."},
        {"name": "Порция", "value": "1 капсула"},
        {"name": "Состав", "value": "Экстракт лопуха — 500 мг"}
      ]
    },
    {
      "slug": "spirulina-1000",
      "name": "Спирулина 1000 мг",
      "short": "Иммунитет, белок, обмен веществ",
      "category": "Суперфуды",
      "image": "images/spirulina.jpg",
      "description": "Поддерживает иммунитет и микрофлору кишечника, богата белком и пищевыми волокнами, помогает регулировать сахар крови и обмен веществ.",
      "facts": [
        {"name": "Форма", "value": "Капсулы, 60 шт."},
        {"name": "Порция", "value": "2 капсулы"},
        {"name": "Состав", "value": "Спирулина — 1000 мг"}
      ]
    },
    {
      "slug": "omega-3-1000",
      "name": "Омега-3 1000 мг",
      "short": "Мозг, сердце, зрение",
      "category": "Жирные кислоты",
      "image": "images/omega-3.jpg",
      "description": "Незаменимые жирные кислоты для работы мозга и сердечно-сосудистой системы, иммунитета и состояния кожи и зрения. Способствуют нормализации липидного обмена.",
      "facts": [
        {"name": "Форма", "value": "Мягкие капсулы, 60 шт."},
        {"name": "Порция", "value": "1 капсула"},
        {"name": "Состав", "value": "Рыбий жир — 1000 мг; EPA — 180 мг; DHA — 120 мг"}
      ]
    },
    {
      "slug": "b-complex",
      "name": "Витамин B-комплекс",
      "short": "Энергия, нервная система, кровь",
      "category": "Витамины",
      "image": "images/b-complex.jpg",
      "description": "Комплекс витаминов группы B для энергообмена, работы ЦНС и кроветворения. Поддерживает синтез гемоглобина и эритроцитов, обмен углеводов.",
      "facts": [
        {"name": "Форма", "value": "Капсулы, 60 шт."},
        {"name": "Порция", "value": "1 капсула"},
        {"name": "Состав на порцию", "value": "B1 — 50 мг; B2 — 50 мг; B3 — 50 мг; B5 — 20 мг; B6 — 10 мг; Биотин — 100 мкг; Инозитол — 50 мг; Фолиевая к-та — 400 мкг; B12 — 50 мкг; Холин — 20 мг"}
      ]
    },
    {
      "slug": "iron-kids",
      "name": "Iron Kids (Железо)",
      "short": "Детское железо, иммунитет и рост",
      "category": "Для детей",
      "image": "images/iron-kids.jpg",
      "description": "Поддерживает иммунитет, участвует в росте и восстановлении тканей. Дефицит железа может приводить к анемии.",
      "facts": [
        {"name": "Форма", "value": "Жидкость, 30 мл"},
        {"name": "Порция", "value": "1 мл"},
        {"name": "Состав", "value": "Железо — 50 мг"}
      ]
    },
    {
      "slug": "propolis-multivitamin",
      "name": "Прополис Мультивитамин & Мультиминерал",
      "short": "Иммуномодулятор, поддержка слизистых",
      "category": "Комплексы",
      "image": "images/propolis-multivitamin.jpg",
      "description": "Натуральный иммуномодулятор с прополисом и набором витаминов и минералов. Поддержка при воспалениях, заживление, помощь ЖКТ.",
      "facts": [
        {"name": "Форма", "value": "Жидкость, 150 мл"},
        {"name": "Порция", "value": "10 мл"},
        {"name": "Состав (на 10 мл)", "value": "Прополис 100 мг; Vit A 1000 МЕ; B1 0.7 мг; B2 0.8 мг; B3 8 мг; B5 5 мг; B6 1 мг; B12 2 мкг; C 60 мг; D 400 МЕ; E 10 мг; K 30 мкг; Медь 340 мкг; Селен 20 мкг; Йод 50 мкг; Цинк 3 мг; Фолиевая к-та 100 мкг; Биотин 15 мкг"}
      ]
    },
    {
      "slug": "womens-multivitamin",
      "name": "Женский Мультивитамин",
      "short": "Ежедневный баланс, усвоение до 98%",
      "category": "Комплексы",
      "image": "images/womens-multivitamin.jpg",
      "description": "Сбалансированный комплекс для женского организма: пищеварение, иммунитет, метаболизм, поддержка кожи и энергии.",
      "facts": [
        {"name": "Форма", "value": "Капсулы, 30 шт."},
        {"name": "Порция", "value": "1 капсула"},
        {"name": "Состав (частично 1)", "value": "Vit C 50 мг; Mg 50 мг; Экстракт клюквы 50 мг; Коэнзим Q10 20 мг; Vit B3 10 мг; Vit B5 100 мкг; Vit E 50 мг; Fe 400 мкг; Zn 7.5 мг; Vit B6 3.3 мг; Холин 2.5 мг; Инозитол 2.5 мг; Медь 2000 мкг; Марганец 2 мг; Vit B2 1.87 мг"},
        {"name": "Состав (частично 2)", "value": "Vit B1 1.65 мг; Лютеин 1 мг; Ликопин 600 мкг; Фолиевая к-та 400 мкг; Vit A 300 мкг (1000 МЕ); Биотин 300 мкг; Хром 200 мкг; Зеаксантин 200 мкг; Йод 150 мкг; Селен 100 мкг; Vit K 80 мкг; Молибден 75 мкг; Vit B12 25 мкг; Vit D 25 мкг (1000 МЕ); Ванадий 10 мкг"}
      ]
    },
    {
      "slug": "vitamin-d3-10000",
      "name": "Витамин D3 10 000 МЕ",
      "short": "Иммунитет, кальциевый обмен, сосуды",
      "category": "Витамины",
      "image": "images/vitamin-d3-10000.jpg",
      "description": "Поддерживает иммунитет и здоровый кальциевый обмен, способствует эластичности сосудов и профилактике кальцификации тканей.",
      "facts": [
        {"name": "Форма", "value": "Жидкость, ~30 доз"},
        {"name": "Порция", "value": "0.5 мл"},
        {"name": "Состав", "value": "Витамин D — 250 мкг (10 000 МЕ)"}
      ]
    },
    {
      "slug": "anti-stress",
      "name": "Анти-Стресс",
      "short": "Спокойствие, сон, снижение тревожности",
      "category": "Растительные экстракты",
      "image": "images/anti-stress.jpg",
      "description": "Поддержка при тревоге и напряжении, нормализация сна. Растительные экстракты зверобоя, пассифлоры и валерианы.",
      "facts": [
        {"name": "Форма", "value": "Капсулы, 30 шт."},
        {"name": "Порция", "value": "1 капсула"},
        {"name": "Состав", "value": "Экстр. зверобоя 300 мг; экстр. пассифлоры 100 мг; экстр. валерианы 100 мг"}
      ]
    },
    {
      "slug": "ca-mg-fe-d3",
      "name": "Ca-Mg-Fe-D3",
      "short": "Кости, кровь, обмен, профилактика дефицитов",
      "category": "Минералы",
      "image": "images/ca-mg-fe-d3.jpg",
      "description": "Сбалансированная комбинация кальция, магния, железа и витамина D для костей, крови и обмена веществ.",
      "facts": [
        {"name": "Форма", "value": "Таблетки, 60 шт."},
        {"name": "Порция", "value": "2 таблетки"},
        {"name": "Состав", "value": "Ca 500 мг; Mg 250 мг; Fe 16 мг; Vit D 15 мкг (600 МЕ)"}
      ]
    },
    {
      "slug": "artichoke-dandelion",
      "name": "Экстракты Артишока и Одуванчика",
      "short": "Печень, желчегонный эффект, обмен",
      "category": "Растительные экстракты",
      "image": "images/artichoke-dandelion.jpg",
      "description": "Поддержка печени и желчевыводящих путей, антиоксидантная защита, мягкий мочегонный эффект.",
      "facts": [
        {"name": "Форма", "value": "Капсулы, 60 шт."},
        {"name": "Порция", "value": "1 капсула"},
        {"name": "Состав", "value": "Экстр. артишока 400 мг; экстр. корня одуванчика 200 мг"}
      ]
    },
    {
      "slug": "st-johns-wort-parsley",
      "name": "Зверобой + Петрушка",
      "short": "Антисептический и седативный эффект",
      "category": "Растительные экстракты",
      "image": "images/st-johns-wort-parsley.jpg",
      "description": "Растительная поддержка: антибактериальные, седативные и регенерирующие свойства; помощь при стрессах и сезонных простудах.",
      "facts": [
        {"name": "Форма", "value": "Капсулы, 60 шт."},
        {"name": "Порция", "value": "2 капсулы"},
        {"name": "Состав", "value": "Экстр. зверобоя 600 мг; экстр. петрушки 200 мг"}
      ]
    },
    {
      "slug": "collagen-30-sachets",
      "name": "Коллаген — 30 саше",
      "short": "Кожа, суставы, волосы и ногти",
      "category": "Коллаген",
      "image": "images/collagen-30-sachets.jpg",
      "description": "Три типа коллагена + витамин C, гиалуроновая кислота, коэнзим Q10, цинк, биотин и витамины группы B для кожи, суставов и общего тонуса.",
      "facts": [
        {"name": "Форма", "value": "Саше, 30 шт."},
        {"name": "Порция", "value": "1 саше"},
        {"name": "Состав (основное)", "value": "Коллаген I/III — 9950 мг; Vit C — 300 мг; ГК — 100 мг; Коллаген II — 50 мг; Vit E — 7 мг; Zn — 5 мг; Q10 — 5 мг; Vit B5 — 3.5 мг; Биотин — 2.5 мг; B6 — 1.4 мг; B12 — 2.5 мкг"}
      ]
    },
    {
      "slug": "zinc-complex",
      "name": "Цинк (комплекс)",
      "short": "Иммунитет, кожа, обмен",
      "category": "Минералы",
      "image": "images/zinc-complex.jpg",
      "description": "Поддержка иммунитета, кожи и обменных процессов. Усилен витамином C, D и селеном.",
      "facts": [
        {"name": "Форма", "value": "Таблетки, 60 шт."},
        {"name": "Порция", "value": "1 таблетка"},
        {"name": "Состав", "value": "Vit C 300 мг (375%); Zn 15 мг (150%); Vit D 1000 МЕ / 25 мкг (500%); Se 70 мкг (127%)"}
      ]
    },
    {
      "slug": "probiotic-30b",
      "name": "Пробиотик",
      "short": "Микробиом и пищеварение",
      "category": "Пробиотики",
      "image": "images/probiotic.jpg",
      "description": "Мультиштаммовый пробиотик: защита от патогенов, синтез витаминов, улучшение всасывания минералов и поддержка иммунитета.",
      "facts": [
        {"name": "Форма", "value": "Капсулы, 30 шт."},
        {"name": "Порция", "value": "1 капсула"},
        {"name": "Штаммы (на дневной приём)", "value": "L. plantarum 4.6×10^9; L. acidophilus 3×10^9; L. paracasei 3×10^9; L. rhamnosus 2.2×10^8; L. brevis 2.2×10^8; S. thermophilus 2.2×10^8; B. bifidum 2×10^8; B. infantis 1.7×10^8; L. reuteri 1.3×10^8; B. longum 3.8×10^7; L. bulgaricus 1.6×10^7"}
      ]
    },
    {
      "slug": "slimming-complex",
      "name": "Слимминг Комплекс",
      "short": "Тонус, метаболизм и контроль аппетита",
      "category": "Комплексы",
      "image": "images/slimming-complex.jpg",
      "description": "Тонизация и поддержка снижения веса: гуарана, зелёный чай, CLA, L-карнитин, гарциния, корица, гимнема, 5-HTP и хром. Повышает выносливость, улучшает концентрацию и ускоряет обмен.",
      "facts": [
        {"name": "Форма", "value": "Капсулы, 60 шт."},
        {"name": "Порция", "value": "1–2 капсулы"},
        {"name": "Состав (на 1 / на 2 капсулы)", "value": "CLA 250 / 500 мг; L-карнитин 100 / 200 мг; Экстр. гуараны 125 / 250 мг; Экстр. зелёного чая 50 / 100 мг; Экстр. «люцерны/маки»* 50 / 100 мг; Гарциния 25 / 50 мг; Корица 25 / 50 мг; Гимнема 25 / 50 мг; 5-HTP 20 / 40 мг; Хром 66 мкг (120/240% ВДН)"},
        {"name": "Примечание", "value": "*По источнику использован термин «Lepidium meyenii» (мака)."}
      ]
    },
    {
      "slug": "ginkgo-syrup",
      "name": "Гинкго Билоба — сироп",
      "short": "Память, мозговое кровообращение",
      "category": "Сиропы",
      "image": "images/ginkgo-syrup.jpg",
      "description": "Поддерживает память, ясность мышления и концентрацию; улучшает мозговое кровообращение, расширяет сосуды и нормализует давление.",
      "facts": [
        {"name": "Форма", "value": "Сироп, 150 мл"},
        {"name": "Порция", "value": "5 мл"},
        {"name": "Состав", "value": "Экстр. листьев Гинкго билоба — 375 мг; Экстр. корейского женьшеня — 20 мг; Цитиколин — 15 мг"}
      ]
    },
    {
      "slug": "tribulus-complex",
      "name": "Demir Dikeni (Трибулус) комплекс",
      "short": "Мужское здоровье, тонус",
      "category": "Растительные экстракты",
      "image": "images/tribulus-complex.jpg",
      "description": "Поддержка мужской репродуктивной функции, выносливости и сосудистой системы. Содержит трибулус, эпимедиум, женьшень, L-аргинин и L-карнитин.",
      "facts": [
        {"name": "Форма", "value": "Капсулы, 60 шт."},
        {"name": "Порция", "value": "2 капсулы"},
        {"name": "Состав (на порцию)", "value": "Экстр. трибулуса (сапонины 900 мг) — 100 мг*; L-аргинин 200 мг; Экстр. эпимедиума 200 мг; Экстр. корейского женьшеня 75 мг; Порошок галангала 75 мг; L-карнитин 100 мг"},
        {"name": "Примечание", "value": "*В источнике указаны и «сапонин 900 мг», и «100 мг» — свёл по тексту каталога."}
      ]
    },
    {
      "slug": "vitamin-c-effervescent-1000",
      "name": "Витамин C 1000 мг (шипучий)",
      "short": "Иммунитет, антиоксидант, коллаген",
      "category": "Витамины",
      "image": "images/vitamin-c-eff.jpg",
      "description": "Поддерживает иммунитет, состояние сосудов и кожи, улучшает усвоение железа и синтез коллагена.",
      "facts": [
        {"name": "Форма", "value": "Шипучие таблетки, 20 шт."},
        {"name": "Порция", "value": "1 таблетка"},
        {"name": "Состав", "value": "Витамин C — 1000 мг (1250% от нормы)"}
      ]
    }
  ]